{
  "versions": [
    { "displayValue": "1.0", "pathSegment": "v1.0", "fallbackLink": "/index.html", "label": "Dev" },
    { "displayValue": "0.23", "pathSegment": "v0.23", "fallbackLink": "/index.html", "label": "Stable" },
    { "displayValue": "0.22", "pathSegment": "v0.22", "fallbackLink": "/index.html", "label": "Stable" },
    { "displayValue": "0.21", "pathSegment": "v0.21", "fallbackLink": "/index.html", "label": "EOL" }
  ],
  "linkTargets": [
    { "path": "/auth.html", "versions": ["v1.0"] },
    { "path": "/client.html", "versions": ["v1.0"] },
    { "path": "/cors.html", "versions": ["v1.0"] },
    { "path": "/csrf.html", "versions": ["v1.0"] },
    { "path": "/deployment.html", "versions": ["v1.0"] },
    { "path": "/dsl.html", "versions": ["v1.0"] },
    { "path": "/entity.html", "versions": ["v1.0"] },
    { "path": "/error-handling.html", "versions": ["v1.0"] },
    { "path": "/gzip.html", "versions": ["v1.0"] },
    { "path": "/hsts.html", "versions": ["v1.0"] },
    { "path": "/index.html", "versions": ["v1.0"] },
    { "path": "/integrations.html", "versions": ["v1.0"] },
    { "path": "/json.html", "versions": ["v1.0"] },
    { "path": "/methods.html", "versions": ["v1.0"] },
    { "path": "/middleware.html", "versions": ["v1.0"] },
    { "path": "/service.html", "versions": ["v1.0"] },
    { "path": "/static.html", "versions": ["v1.0"] },
    { "path": "/streaming.html", "versions": ["v1.0"] },
    { "path": "/testing.html", "versions": ["v1.0"] },
    { "path": "/upgrading.html", "versions": ["v1.0"] },
    { "path": "/uri.html", "versions": ["v1.0"] }
  ]
}